grovec_sv_solution/__init__.py
grovec_sv_solution/grovec_sv_solution.py
grovec_sv_solution/neo_data_ingestion_dag.py
grovec_sv_solution-0.1.16.dist-info/entry_points.txt
grovec_sv_solution-0.1.16.dist-info/LICENSE
grovec_sv_solution-0.1.16.dist-info/WHEEL
grovec_sv_solution-0.1.16.dist-info/METADATA
grovec_sv_solution-0.1.16.dist-info/RECORD
